asciinemaster/__init__.py
asciinemaster/asciinemaster.py
asciinemaster/cli.py
asciinemaster-0.2.0.dist-info/DESCRIPTION.rst
asciinemaster-0.2.0.dist-info/METADATA
asciinemaster-0.2.0.dist-info/RECORD
asciinemaster-0.2.0.dist-info/WHEEL
asciinemaster-0.2.0.dist-info/entry_points.txt
asciinemaster-0.2.0.dist-info/metadata.json
asciinemaster-0.2.0.dist-info/top_level.txt
