Metadata-Version: 2.0
Name: asciinemaster
Version: 0.2.0
Summary: Asciinemaster contains some experiments to add features to drive Asciinema.
Home-page: https://github.com/deeplook/asciinemaster
Author: Dinu Gherman
Author-email: gherman@darwin.in-berlin.de
License: GNU General Public License v3
Keywords: asciinemaster
Platform: UNKNOWN
Classifier: Development Status :: 2 - Pre-Alpha
Classifier: Intended Audience :: Developers
Classifier: License :: OSI Approved :: GNU General Public License v3 (GPLv3)
Classifier: Natural Language :: English
Classifier: Programming Language :: Python :: 2
Classifier: Programming Language :: Python :: 2.7
Classifier: Programming Language :: Python :: 3
Classifier: Programming Language :: Python :: 3.4
Classifier: Programming Language :: Python :: 3.5
Classifier: Programming Language :: Python :: 3.6
Classifier: Programming Language :: Python :: Implementation :: CPython
Classifier: Programming Language :: Python :: Implementation :: PyPy
Requires-Dist: capturer (>=2.4)
